moshpit
