Metadata-Version: 1.1
Name: MoshPit
Version: 2.0
Summary: A wrapper for mosh.  Save hosts and connect to them by nickname.
Home-page: http://moshpit.aj7may.com
Author: A.J. May
Author-email: UNKNOWN
License: Creative Commons Attribution-ShareAlike 3.0 Unported License
Platform: UNKNOWN
Requires: SQLAlchemy(>0.8.0)
